LICENSE
MANIFEST.in
README.md
requirements.txt
requirements_test.txt
setup.cfg
setup.py
whatever_rest_framework.egg-info/PKG-INFO
whatever_rest_framework.egg-info/SOURCES.txt
whatever_rest_framework.egg-info/dependency_links.txt
whatever_rest_framework.egg-info/requires.txt
whatever_rest_framework.egg-info/top_level.txt
wrf/__init__.py
wrf/base.py
wrf/compat.py
wrf/api/__init__.py
wrf/api/base.py
wrf/error/__init__.py
wrf/error/base.py
wrf/framework/__init__.py
wrf/framework/base.py
wrf/framework/chalice.py
wrf/framework/django.py
wrf/framework/falcon.py
wrf/framework/flask.py
wrf/framework/pyramid.py
wrf/orm/__init__.py
wrf/orm/base.py
wrf/orm/django.py
wrf/orm/peewee.py
wrf/orm/sqlalchemy.py
wrf/pagination/__init__.py
wrf/pagination/base.py
wrf/permission/__init__.py
wrf/permission/base.py
wrf/schema/__init__.py
wrf/schema/base.py
wrf/schema/marshmallow.py
wrf/schema/marshmallow_sqlalchemy.py