Metadata-Version: 2.1
Name: whatever-rest-framework
Version: 0.5.0
Summary: RESTful API framework for your project, whatever tools you are using.
Home-page: https://github.com/filwaitman/whatever-rest-framework
Author: Filipe Waitman
Author-email: filwaitman@gmail.com
License: UNKNOWN
Download-URL: https://github.com/filwaitman/whatever-rest-framework/tarball/0.5.0
Platform: UNKNOWN
Classifier: Development Status :: 3 - Alpha
Classifier: Intended Audience :: Developers
Classifier: License :: OSI Approved :: MIT License
Classifier: Operating System :: OS Independent
Classifier: Framework :: Flask
Classifier: Framework :: Pyramid
